holvirc/__init__.py
holvirc/categories.py
holvirc/chromedriver.py
holvirc/connection.py
holvirc/helpers.py
holvirc/tests/__init__.py
holvirc/tests/fixtures.py
holvirc/tests/test_holviapi_dangerous.py
holvirc/tests/test_holviapi_idempotent.py
holvirc/tests/test_slow_things.py
holvirc-0.3.20190209.dist-info/LICENSE
holvirc-0.3.20190209.dist-info/METADATA
holvirc-0.3.20190209.dist-info/WHEEL
holvirc-0.3.20190209.dist-info/top_level.txt
holvirc-0.3.20190209.dist-info/RECORD
