Metadata-Version: 2.1
Name: holvirc
Version: 0.3.20190209
Summary: Remote-Control Holvi via Selenium
Home-page: https://github.com/rambo/python-holvirc
Author: Eero "rambo" af Heurlin
Author-email: rambo@iki.fi
License: MIT
Platform: UNKNOWN
Requires-Dist: six (==1.12.0)
Requires-Dist: future (==0.17.1)
Requires-Dist: requests (==2.21.0)
Requires-Dist: requests-cache (==0.4.13)
Requires-Dist: python-dateutil (==2.7.5)
Requires-Dist: holviapi (>=0.6.20190131)
